bambara_normalizer/__init__.py
bambara_normalizer/cli/__init__.py
bambara_normalizer/normalizers/__init__.py
bambara_normalizer/normalizers/bam_asr_normalizer.py
bambara_normalizer/normalizers/bambara_number_normalizer.py
bambara_normalizer/normalizers/basic_bam_normalizer.py
bambara_normalizer/normalizers/basic_text_normalizer.py
bambara_normalizer/utils/__init__.py
bambara_normalizer-1.0.0.dist-info/METADATA
bambara_normalizer-1.0.0.dist-info/WHEEL
bambara_normalizer-1.0.0.dist-info/licenses/LICENSE
bambara_normalizer-1.0.0.dist-info/RECORD
