Metadata-Version: 2.4
Name: bambara-normalizer
Version: 1.0.0
Summary: A python package for normalizing Bambara text for NLP
Project-URL: Issues, https://github.com/diarray-hub/bambara-normalizer/issues
Project-URL: Source, https://github.com/diarray-hub/bambara-normalizer
Author-email: Yacouba Diarra <diarray@robotsmali.org>
License-Expression: MIT
License-File: LICENSE
Keywords: NLP,bambara,diacritic removal,natural language processing,text normalization,text preprocessing
Classifier: License :: OSI Approved :: MIT License
Classifier: Operating System :: OS Independent
Classifier: Programming Language :: Python :: 3
Classifier: Programming Language :: Python :: 3.9
Classifier: Programming Language :: Python :: 3.10
Classifier: Programming Language :: Python :: 3.11
Classifier: Programming Language :: Python :: 3.12
Classifier: Programming Language :: Python :: 3.13
Requires-Python: >=3.9
